neurobiba
